README.rst
setup.py
wdc
webdav/__init__.py
webdav/client.py
webdav/connection.py
webdav/exceptions.py
webdav/urn.py
webdavclient.egg-info/PKG-INFO
webdavclient.egg-info/SOURCES.txt
webdavclient.egg-info/dependency_links.txt
webdavclient.egg-info/requires.txt
webdavclient.egg-info/top_level.txt