Metadata-Version: 1.1
Name: webdavclient
Version: 1.0.0
Summary: Webdav API, resource API и wdc для WebDAV-серверов (Yandex.Disk, Dropbox, Google Disk, Box, 4shared и т.д.)
Home-page: https://github.com/designerror/webdavclient
Author: Designerror
Author-email: designerror@yandex.ru
License: MIT License
Download-URL: https://github.com/designerror/webdavclient/tarball/master
Keywords: webdav,client,python,module,library,packet,Yandex.Disk,Dropbox,Google Disk,Box,4shared
Platform: UNKNOWN
Classifier: Environment :: Console
Classifier: Environment :: Web Environment
Classifier: License :: OSI Approved :: MIT License
Classifier: Operating System :: MacOS
Classifier: Operating System :: Microsoft
Classifier: Operating System :: Unix
Classifier: Programming Language :: Python :: 2.6
Classifier: Programming Language :: Python :: 2.7
Classifier: Programming Language :: Python :: 3.0
Classifier: Programming Language :: Python :: 3.1
Classifier: Programming Language :: Python :: 3.2
Classifier: Programming Language :: Python :: 3.3
Classifier: Programming Language :: Python :: 3.4
Classifier: Topic :: Internet
Classifier: Topic :: Software Development :: Libraries :: Python Modules
Requires: python (>= 2.7.6)
